my_app/__init__.py
my_app/_version.py
my_app/my_app.py
indiejobs_cli-1.0.11.dist-info/METADATA
indiejobs_cli-1.0.11.dist-info/WHEEL
indiejobs_cli-1.0.11.dist-info/entry_points.txt
indiejobs_cli-1.0.11.dist-info/top_level.txt
indiejobs_cli-1.0.11.dist-info/RECORD
