Metadata-Version: 2.1
Name: indiejobs-cli
Version: 1.0.11
Summary: IndieJobs - Autojobs CLI tool
Home-page: https://github.com/FranciscoRSilva/indiejobs-cli
Author: FranciscoRSilva
Author-email: francisco.silva@indiecampers.com
Classifier: Programming Language :: Python :: 3.8
